sweetrpg_catalog_objects/__init__.py
sweetrpg_catalog_objects/api/__init__.py
sweetrpg_catalog_objects/api/contribution/__init__.py
sweetrpg_catalog_objects/api/contribution/schema.py
sweetrpg_catalog_objects/api/license/__init__.py
sweetrpg_catalog_objects/api/license/schema.py
sweetrpg_catalog_objects/api/person/__init__.py
sweetrpg_catalog_objects/api/person/schema.py
sweetrpg_catalog_objects/api/publisher/__init__.py
sweetrpg_catalog_objects/api/publisher/schema.py
sweetrpg_catalog_objects/api/review/__init__.py
sweetrpg_catalog_objects/api/review/schema.py
sweetrpg_catalog_objects/api/studio/__init__.py
sweetrpg_catalog_objects/api/studio/schema.py
sweetrpg_catalog_objects/api/system/__init__.py
sweetrpg_catalog_objects/api/system/schema.py
sweetrpg_catalog_objects/api/volume/__init__.py
sweetrpg_catalog_objects/api/volume/schema.py
sweetrpg_catalog_objects/db/__init__.py
sweetrpg_catalog_objects/db/contribution/__init__.py
sweetrpg_catalog_objects/db/contribution/document.py
sweetrpg_catalog_objects/db/contribution/schema.py
sweetrpg_catalog_objects/db/embedded/__init__.py
sweetrpg_catalog_objects/db/embedded/property/__init__.py
sweetrpg_catalog_objects/db/embedded/property/document.py
sweetrpg_catalog_objects/db/embedded/property/schema.py
sweetrpg_catalog_objects/db/embedded/tag/__init__.py
sweetrpg_catalog_objects/db/embedded/tag/document.py
sweetrpg_catalog_objects/db/embedded/tag/schema.py
sweetrpg_catalog_objects/db/license/__init__.py
sweetrpg_catalog_objects/db/license/document.py
sweetrpg_catalog_objects/db/license/schema.py
sweetrpg_catalog_objects/db/person/__init__.py
sweetrpg_catalog_objects/db/person/document.py
sweetrpg_catalog_objects/db/person/schema.py
sweetrpg_catalog_objects/db/publisher/__init__.py
sweetrpg_catalog_objects/db/publisher/document.py
sweetrpg_catalog_objects/db/publisher/schema.py
sweetrpg_catalog_objects/db/review/__init__.py
sweetrpg_catalog_objects/db/review/document.py
sweetrpg_catalog_objects/db/review/schema.py
sweetrpg_catalog_objects-0.0.175.dist-info/LICENSE
sweetrpg_catalog_objects-0.0.175.dist-info/METADATA
sweetrpg_catalog_objects-0.0.175.dist-info/WHEEL
sweetrpg_catalog_objects-0.0.175.dist-info/entry_points.txt
sweetrpg_catalog_objects-0.0.175.dist-info/top_level.txt
sweetrpg_catalog_objects-0.0.175.dist-info/RECORD
